assertpy-stubs/__init__.pyi
assertpy-stubs/assertpy.pyi
assertpy-stubs/base.pyi
assertpy-stubs/collection.pyi
assertpy-stubs/contains.pyi
assertpy-stubs/date.pyi
assertpy-stubs/dict.pyi
assertpy-stubs/dynamic.pyi
assertpy-stubs/exception.pyi
assertpy-stubs/extracting.pyi
assertpy-stubs/file.pyi
assertpy-stubs/helpers.pyi
assertpy-stubs/numeric.pyi
assertpy-stubs/snapshot.pyi
assertpy-stubs/string.pyi
assertpy_stubs-1.1.2.dist-info/LICENSE
assertpy_stubs-1.1.2.dist-info/METADATA
assertpy_stubs-1.1.2.dist-info/WHEEL
assertpy_stubs-1.1.2.dist-info/RECORD
