Metadata-Version: 2.1
Name: assertpy-stubs
Version: 1.1.2
Summary: Mypy|Pyright plugin and stubs for assertpy
Home-page: https://github.com/socgnachilderic/assertpy-stubs
License: MIT
Keywords: mypy,pyright,assertpy,stubs
Author: SOCGNA KOUYEM Childeric
Author-email: socgnachilderic@proton.me
Maintainer: SOCGNA KOUYEM Childeric
Maintainer-email: socgnachilderic@proton.me
Requires-Python: >=3.9
Classifier: Development Status :: 4 - Beta
Classifier: Intended Audience :: Developers
Classifier: License :: OSI Approved :: MIT License
Classifier: Natural Language :: English
Classifier: Programming Language :: Python :: 3
Classifier: Programming Language :: Python :: 3.9
Classifier: Programming Language :: Python :: 3.10
Classifier: Programming Language :: Python :: 3.11
Classifier: Programming Language :: Python :: 3.12
Requires-Dist: assertpy (>=1.1,<2.0)
Requires-Dist: typing-extensions (>=4.12.2,<5.0.0)
Project-URL: Repository, https://github.com/socgnachilderic/assertpy-stubs
